taskiq_aws/__init__.py
taskiq_aws/sqs_broker.py
taskiq_aws-0.4.0.dist-info/LICENSE
taskiq_aws-0.4.0.dist-info/METADATA
taskiq_aws-0.4.0.dist-info/WHEEL
taskiq_aws-0.4.0.dist-info/RECORD
