Metadata-Version: 2.1
Name: taskiq-aws
Version: 0.4.0
Summary: 
License: LICENSE
Keywords: taskiq,tasks,distributed,async
Author: Taskiq team
Author-email: taskiq@no-reply.com
Maintainer: Taskiq team
Maintainer-email: taskiq@no-reply.com
Requires-Python: >=3.8.1,<4.0.0
Classifier: Development Status :: 3 - Alpha
Classifier: Intended Audience :: Developers
Classifier: License :: Other/Proprietary License
Classifier: Operating System :: OS Independent
Classifier: Programming Language :: Python
Classifier: Programming Language :: Python :: 3
Classifier: Programming Language :: Python :: 3.9
Classifier: Programming Language :: Python :: 3.10
Classifier: Programming Language :: Python :: 3.11
Classifier: Programming Language :: Python :: 3.12
Classifier: Programming Language :: Python :: 3 :: Only
Classifier: Programming Language :: Python :: 3.8
Classifier: Topic :: System :: Networking
Classifier: Typing :: Typed
Requires-Dist: aiobotocore (>=2.13.1,<3.0.0)
Requires-Dist: taskiq (>=0,<1)
Requires-Dist: wait-for-it (>=2.2.2,<3.0.0)
